uniquebible/htmlResources/images/exlbl_largeHD_2/BL401.png
uniquebible/htmlResources/images/exlbl_largeHD_2/BL402.png
uniquebible/htmlResources/images/exlbl_largeHD_2/BL403.png
uniquebible/htmlResources/images/exlbl_largeHD_2/BL404.png
uniquebible/htmlResources/images/exlbl_largeHD_2/BL406.png
uniquebible/htmlResources/images/exlbl_largeHD_2/BL407.png
uniquebible/htmlResources/images/exlbl_largeHD_2/BL408.png
uniquebible/htmlResources/images/exlbl_largeHD_2/BL409.png
uniquebible/htmlResources/images/exlbl_largeHD_2/BL410.png
uniquebible/htmlResources/images/exlbl_largeHD_2/BL411.png
uniquebible/htmlResources/images/exlbl_largeHD_2/BL412.png
uniquebible/htmlResources/images/exlbl_largeHD_2/BL413.png
uniquebible/htmlResources/images/exlbl_largeHD_2/BL414.png
uniquebible/htmlResources/images/exlbl_largeHD_2/BL415.png
uniquebible/htmlResources/images/exlbl_largeHD_2/BL416.png
uniquebible/htmlResources/images/exlbl_largeHD_2/BL417.png
uniquebible/htmlResources/images/exlbl_largeHD_2/BL418.png
uniquebible/htmlResources/images/exlbl_largeHD_2/BL419.png
uniquebible/htmlResources/images/exlbl_largeHD_2/BL420.png
uniquebible/htmlResources/images/exlbl_largeHD_2/BL421.png
uniquebible/htmlResources/images/exlbl_largeHD_2/BL422.png
uniquebible/htmlResources/images/exlbl_largeHD_2/BL423.png
uniquebible/htmlResources/images/exlbl_largeHD_2/BL424.png
uniquebible/htmlResources/images/exlbl_largeHD_2/BL427.png
uniquebible/htmlResources/images/exlbl_largeHD_2/BL429.png
uniquebible/htmlResources/images/exlbl_largeHD_2/BL430.png
uniquebible/htmlResources/images/exlbl_largeHD_2/BL431.png
uniquebible/htmlResources/images/exlbl_largeHD_2/BL432.png
uniquebible/htmlResources/images/exlbl_largeHD_2/BL433.png
uniquebible/htmlResources/images/exlbl_largeHD_2/BL434.png
uniquebible/htmlResources/images/exlbl_largeHD_2/BL435.png
uniquebible/htmlResources/images/exlbl_largeHD_2/BL436.png
uniquebible/htmlResources/images/exlbl_largeHD_2/BL438.png
uniquebible_maps_4-0.0.3.dist-info/LICENSE
uniquebible_maps_4-0.0.3.dist-info/METADATA
uniquebible_maps_4-0.0.3.dist-info/WHEEL
uniquebible_maps_4-0.0.3.dist-info/top_level.txt
uniquebible_maps_4-0.0.3.dist-info/RECORD
